anycurve/__init__.py
anycurve/curve.py
anycurve/database.py
anycurve/plot.py
anycurve-0.2.0.dist-info/LICENSE
anycurve-0.2.0.dist-info/METADATA
anycurve-0.2.0.dist-info/WHEEL
anycurve-0.2.0.dist-info/top_level.txt
anycurve-0.2.0.dist-info/RECORD
