Metadata-Version: 2.1
Name: anycurve
Version: 0.2.0
Summary: A data visualization toolbox
Home-page: http://hwfan.io
Author: hwfan
Author-email: hwnorm@outlook.com
License: Apache
Keywords: anycurve,curve,plot,hwfan
Platform: any
Requires-Dist: pandas
Requires-Dist: numpy
Requires-Dist: lmdb
Requires-Dist: matplotlib
